AUTHORS
CHANGELOG.txt
DESCRIPTION
LICENSE
MANIFEST.in
README.rst
setup.py
cmsplugin_markdown/__init__.py
cmsplugin_markdown/cms_plugins.py
cmsplugin_markdown/models.py
cmsplugin_markdown/utils.py
cmsplugin_markdown.egg-info/PKG-INFO
cmsplugin_markdown.egg-info/SOURCES.txt
cmsplugin_markdown.egg-info/dependency_links.txt
cmsplugin_markdown.egg-info/requires.txt
cmsplugin_markdown.egg-info/top_level.txt
cmsplugin_markdown/migrations/0001_initial.py
cmsplugin_markdown/migrations/__init__.py
cmsplugin_markdown/south_migrations/0001_initial.py
cmsplugin_markdown/south_migrations/0002_auto__del_field_markdownplugin_text__add_field_markdownplugin_markdown.py
cmsplugin_markdown/south_migrations/0003_renametable.py
cmsplugin_markdown/south_migrations/__init__.py
cmsplugin_markdown/static/cmsplugin_markdown/images/edit.png
cmsplugin_markdown/static/cmsplugin_markdown/images/fullscreen.png
cmsplugin_markdown/static/cmsplugin_markdown/images/preview.png
cmsplugin_markdown/static/cmsplugin_markdown/js/epiceditor.js
cmsplugin_markdown/static/cmsplugin_markdown/js/epiceditor.min.js
cmsplugin_markdown/static/cmsplugin_markdown/themes/base/epiceditor.css
cmsplugin_markdown/static/cmsplugin_markdown/themes/editor/epic-dark.css
cmsplugin_markdown/static/cmsplugin_markdown/themes/editor/epic-light.css
cmsplugin_markdown/static/cmsplugin_markdown/themes/preview/github.css
cmsplugin_markdown/static/cmsplugin_markdown/themes/preview/preview-dark.css
cmsplugin_markdown/templates/cmsplugin_markdown/change_form.html
cmsplugin_markdown/templates/cmsplugin_markdown/markdown.html
cmsplugin_markdown/tests/__init__.py
cmsplugin_markdown/tests/models_tests.py
cmsplugin_markdown/tests/settings.py
cmsplugin_markdown/tests/test_settings.py
cmsplugin_markdown/tests/urls.py
cmsplugin_markdown/tests/templates/base.html