Metadata-Version: 1.0
Name: cmsplugin-markdown
Version: 0.1.5
Summary: A plugin for django-cms that aims to replace the standard text plugin with it's
